{
  "formatVersion": 1,
  "database": {
    "version": 2,
    "identityHash": "39dc1a5d8c51f1cf8607428db8cbea8a",
    "entities": [
      {
        "tableName": "Products",
        "createSql": "CREATE TABLE IF NOT EXISTS `${TABLE_NAME}` (`_id` TEXT NOT NULL, `product_Name` TEXT NOT NULL, `quantity` INTEGER NOT NULL, `date` TEXT NOT NULL, `checked` INTEGER NOT NULL, PRIMARY KEY(`_id`))",
        "fields": [
          {
            "fieldPath": "_id",
            "columnName": "_id",
            "affinity": "TEXT",
            "notNull": true
          },
          {
            "fieldPath": "product_Name",
            "columnName": "product_Name",
            "affinity": "TEXT",
            "notNull": true
          },
          {
            "fieldPath": "quantity",
            "columnName": "quantity",
            "affinity": "INTEGER",
            "notNull": true
          },
          {
            "fieldPath": "date",
            "columnName": "date",
            "affinity": "TEXT",
            "notNull": true
          },
          {
            "fieldPath": "checked",
            "columnName": "checked",
            "affinity": "INTEGER",
            "notNull": true
          }
        ],
        "primaryKey": {
          "autoGenerate": false,
          "columnNames": [
            "_id"
          ]
        },
        "indices": [],
        "foreignKeys": []
      }
    ],
    "views": [],
    "setupQueries": [
      "CREATE TABLE IF NOT EXISTS room_master_table (id INTEGER PRIMARY KEY,identity_hash TEXT)",
      "INSERT OR REPLACE INTO room_master_table (id,identity_hash) VALUES(42, '39dc1a5d8c51f1cf8607428db8cbea8a')"
    ]
  }
}